{
  "meta": { "name": "六爻旬空月破知识库", "version": "1.0", "note": "包含旬空、月破、日破、暗动、日辰合冲等进阶知识" },
  "entries": [
    {
      "id": "xunkong_gainian",
      "title": "旬空概念",
      "category": "旬空基础",
      "content": "旬空即旬中空亡，是六爻预测中的重要概念。天干有十，地支有十二，一旬十日，必有两个地支轮空，即为旬空。旬空主事情空虚、不实、无力、待时。",
      "detail": "甲子旬中戌亥空，甲戌旬中申酉空，甲申旬中午未空，甲午旬中辰巳空，甲辰旬中寅卯空，甲寅旬中子丑空。旬空之爻力量减弱，但并非完全无力。",
      "check": "查日辰所在旬，确定空亡地支"
    },
    {
      "id": "xunkong_zhonglei",
      "title": "旬空种类",
      "category": "旬空基础",
      "content": "旬空分为真空和假空。真空为爻休囚无气又逢空，主事情彻底无望；假空为爻旺相有气又逢空，主事情暂时不实，待出空可成。",
      "detail": "真空：爻休囚（在月令中休囚），又无动爻生扶，又逢旬空。假空：爻旺相（在月令中旺相），或有动爻生扶，又逢旬空。真空主彻底无望，假空主暂时不实。",
      "method": "1.看爻在月令中的旺衰；2.看有无动爻生扶；3.判断真空假空"
    },
    {
      "id": "xunkong_chukong",
      "title": "出空与填实",
      "category": "旬空基础",
      "content": "出空即旬空之爻遇到冲空或临空之时，力量恢复。填实即旬空之爻遇到空亡地支出现之时，力量充实。出空填实是判断应期的重要方法。",
      "detail": "冲空：旬空地支被冲之时，如戌空遇辰冲则出空。临空：旬空地支出现之时，如戌空遇戌日则填实。出空后爻的力量恢复，事情可成。",
      "method": "1.确定旬空地支；2.找冲空或临空之时；3.判断出空时间"
    },
    {
      "id": "xunkong_yongshen",
      "title": "用神旬空",
      "category": "旬空应用",
      "content": "用神旬空主所问之事空虚不实。真空则事情难成，假空则暂时不实待时可成。用神旬空需看出空时间和方式。",
      "detail": "用神真空：所问之事彻底无望，不宜坚持。用神假空：所问之事暂时不实，待出空可成。用神旬空被日辰冲：冲空则实，事情可成。用神旬空被月建冲：月破兼旬空，事情大凶。",
      "method": "1.看用神是否旬空；2.判断真空假空；3.看出空方式；4.综合判断"
    },
    {
      "id": "xunkong_dongyao",
      "title": "动爻旬空",
      "category": "旬空应用",
      "content": "动爻旬空主事情变化空虚不实。动爻旬空则变化无力，动而不实。但动爻旬空出空后仍可发力。",
      "detail": "动爻旬空：变化暂时不实，待出空后变化实现。动爻旬空被冲：冲空则实，变化加速实现。动爻旬空化进：出空后进步。动爻旬空化退：出空后退步。",
      "method": "1.找动爻；2.看动爻是否旬空；3.看出空方式；4.综合判断变化"
    },
    {
      "id": "xunkong_shiying",
      "title": "世应旬空",
      "category": "旬空应用",
      "content": "世爻旬空主求测者自身空虚不实，应爻旬空主对方空虚不实。世应旬空可判断双方的状态和诚意。",
      "detail": "世爻旬空：求测者自身无力、不实、缺乏诚意。应爻旬空：对方无力、不实、缺乏诚意。世应皆空：双方皆不实，事情难成。世空应不空：求测者不实，对方有诚意。",
      "method": "1.看世爻是否旬空；2.看应爻是否旬空；3.判断双方状态；4.综合判断"
    },
    {
      "id": "yuepo_gainian",
      "title": "月破概念",
      "category": "月破基础",
      "content": "月破即月建冲爻，被冲之爻称为月破。月破之爻力量大减，主事情破败、破损、不成。月破比旬空更严重，主事情根本受损。",
      "detail": "月破查法：月建地支冲爻之地支。如月建子，冲午爻，则午爻月破。月破之爻在当月力量极弱，事情多破败。",
      "check": "查月建地支，看是否冲用神或世爻"
    },
    {
      "id": "yuepo_zhonglei",
      "title": "月破种类",
      "category": "月破基础",
      "content": "月破分为真破和假破。真破为爻休囚又逢月破，主事情彻底破败；假破为爻旺相又逢月破，主事情暂时破损，待合破可成。",
      "detail": "真破：爻在月令中休囚（不得令），又逢月建冲破。假破：爻在月令中旺相（得令），又逢月建冲破。真破主彻底破败，假破主暂时破损。",
      "method": "1.看爻在月令中的旺衰；2.看是否逢月建冲；3.判断真破假破"
    },
    {
      "id": "yuepo_hepo",
      "title": "合破与出破",
      "category": "月破基础",
      "content": "合破即月破之爻遇到合住月建的地支，可解月破。出破即月破之爻过了当月，月建换后自然出破。合破出破是判断应期的重要方法。",
      "detail": "合破：月建子破午爻，遇丑合子则可解破。出破：过了子月，月建换丑，午爻自然出破。出破后爻的力量恢复，事情可成。",
      "method": "1.确定月破地支；2.找合破或出破之时；3.判断恢复时间"
    },
    {
      "id": "yuepo_yongshen",
      "title": "用神月破",
      "category": "月破应用",
      "content": "用神月破主所问之事破败。真破则事情彻底无望，假破则暂时破损待合破可成。用神月破需看出破时间和方式。",
      "detail": "用神真破：所问之事彻底破败，不宜坚持。用神假破：所问之事暂时破损，待出破可成。用神月破被日辰合：合破则实，事情可成。用神月破兼旬空：破空交加，事情大凶。",
      "method": "1.看用神是否月破；2.判断真破假破；3.看出破方式；4.综合判断"
    },
    {
      "id": "ripo_gainian",
      "title": "日破概念",
      "category": "日破基础",
      "content": "日破即日辰冲爻，被冲之爻称为日破。日破之爻力量减弱，但不如月破严重。日破主事情当日受损，但过后可恢复。",
      "detail": "日破查法：日辰地支冲爻之地支。如日辰子，冲午爻，则午爻日破。日破之爻当日力量减弱，但过后力量恢复。",
      "check": "查日辰地支，看是否冲用神或世爻"
    },
    {
      "id": "ripo_yongshen",
      "title": "用神日破",
      "category": "日破应用",
      "content": "用神日破主所问之事当日受损。但日破不如月破严重，过后可恢复。用神日破需看是否兼月破旬空。",
      "detail": "用神日破：所问之事当日有阻，但过后可成。用神日破兼月破：破上加破，事情大凶。用神日破兼旬空：空破交加，事情不实。用神日破被月建合：合住日破，事情可成。",
      "method": "1.看用神是否日破；2.看是否兼月破旬空；3.综合判断"
    },
    {
      "id": "andong_gainian",
      "title": "暗动概念",
      "category": "暗动基础",
      "content": "暗动即静爻被日辰冲而暗动。暗动之爻虽无明动，但被日辰冲动，有暗中的变化。暗动主暗中变化、暗中发力。",
      "detail": "暗动条件：静爻（不发动）被日辰冲。暗动之爻有力量但不如明动大。暗动可生克他爻，也可被其他爻生克。暗动主暗中变化，不明显但有力。",
      "method": "1.找静爻；2.看是否被日辰冲；3.判断暗动；4.看暗动作用"
    },
    {
      "id": "andong_yongshen",
      "title": "用神暗动",
      "category": "暗动应用",
      "content": "用神暗动主所问之事有暗中变化。暗动之用神有暗中发力，事情暗中进展。暗动不如明动明显，但同样有力。",
      "detail": "用神暗动：所问之事暗中进展，不明显但有变化。用神暗动生世：暗中助身。用神暗动克世：暗中伤身。用神暗动被合：暗动被合住，暗中变化受阻。",
      "method": "1.看用神是否暗动；2.看暗动方向；3.综合判断"
    },
    {
      "id": "rihe_gainian",
      "title": "日辰合爻",
      "category": "合冲基础",
      "content": "日辰合爻即日辰地支与爻地支相合。合主合住、合作、和合。日辰合爻可解冲、解破、解空，也可合住动爻使其不能发挥作用。",
      "detail": "六合：子丑合、寅亥合、卯戌合、辰酉合、巳申合、午未合。日辰合爻：合住动爻则动爻不能生克；合住破爻则解破；合住空爻则填空。",
      "method": "1.看日辰地支；2.看是否合爻；3.判断合的作用"
    },
    {
      "id": "rihe_dongyao",
      "title": "日辰合动爻",
      "category": "合冲应用",
      "content": "日辰合动爻主动爻被合住，不能发挥作用。动爻被合住则变化不能实现，事情受阻。但动爻旺相则可冲开合住。",
      "detail": "日辰合动爻：动爻被合住，变化不能实现。动爻旺相：可冲开合住，变化仍可发生。动爻休囚：被合住则变化彻底受阻。",
      "method": "1.找动爻；2.看是否被日辰合；3.看动爻旺衰；4.判断能否冲开"
    },
    {
      "id": "yuejian_shengke",
      "title": "月建生克",
      "category": "月建应用",
      "content": "月建即占断当月的地支，月建对卦中各爻有生克权。月建生爻则爻旺，月建克爻则爻衰。月建是判断爻旺衰的重要依据。",
      "detail": "月建生爻：爻得月建生扶，力量增强。月建克爻：爻被月建克制，力量减弱。月建比和：爻与月建五行相同，力量增强。月建冲爻：爻被月建冲破，力量大减。",
      "method": "1.确定月建；2.看月建与各爻关系；3.判断生克冲合；4.综合判断旺衰"
    },
    {
      "id": "rijian_shengke",
      "title": "日辰生克",
      "category": "日辰应用",
      "content": "日辰即占断当日的地支，日辰对卦中各爻有生克权。日辰生爻则爻旺，日辰克爻则爻衰。日辰可冲空、合破、生克动爻。",
      "detail": "日辰生爻：爻得日辰生扶，力量增强。日辰克爻：爻被日辰克制，力量减弱。日辰冲爻：静爻暗动，动爻加速。日辰合爻：合住动爻，解破填空。",
      "method": "1.确定日辰；2.看日辰与各爻关系；3.判断生克冲合；4.综合判断"
    },
    {
      "id": "xunkong_yuepo_diehe",
      "title": "旬空月破叠合",
      "category": "综合判断",
      "content": "旬空月破叠合即爻既旬空又月破，为空破交加。空破交加主事情彻底无望，力量极弱。但若有日辰生扶或动爻生扶，仍可有一线生机。",
      "detail": "空破交加：爻既旬空又月破，力量极弱，事情彻底无望。空破兼动：动而空破，变化无力。空破得日生：日辰生扶，有一线生机。空破得动生：动爻生扶，有一线生机。",
      "method": "1.看爻是否旬空；2.看爻是否月破；3.看有无生扶；4.综合判断"
    }
  ]
}
