{
  "id": "qimen_fengshui_jiehe",
  "name": "奇门风水结合知识库",
  "version": "1.0.0",
  "description": "奇门遁甲与风水结合应用：择日+布局/八门+八宅/值符方位/案例",
  "entries": [
    {
      "id": "qfjh_01",
      "category": "结合总论",
      "title": "奇门风水结合的必要性",
      "content": "奇门重天时（择日择时），风水重地理（空间布局）。古人云：'天时不如地利，地利不如人和'，实际三者缺一不可。奇门选吉时做事 + 风水吉位布局 + 人和努力 = 完美组合。倪海厦先生强调：'奇门是'天时'，风水是'地利'，二者同参可上应天时下择地利，事半功倍'。现代应用：新居入伙、商业开张、婚嫁择日等都需奇门+风水双重把关。"
    },
    {
      "id": "qfjh_02",
      "category": "择日布局",
      "title": "新居入伙：奇门择日+风水布局",
      "content": "完整流程：1. 八字定户主喜用神（如喜金则西方为主） 2. 风水定户型坐向（八宅或玄空） 3. 奇门择日入伙（用事盘选天盘吉时） 4. 奇门盘选开门或生门方位作为大门朝向 5. 入住时奇门值符方位摆放镇宅符 6. 八宅四吉方摆放主卧/书房。案例：北京某新居，户主八字喜火，玄空飞星 5 黄到向不利，奇门择 3 月 6 日辰时入伙，开门到西南方（生门），化解 5 黄后入住大吉。"
    },
    {
      "id": "qfjh_03",
      "category": "择日布局",
      "title": "商业开张：奇门择日+店铺风水",
      "content": "商业开张要素：1. 老板八字喜用神定行业五行 2. 店铺坐向看玄空飞星（如坐北朝南 8 白到向大吉） 3. 奇门择开张日（避开五黄月、日） 4. 奇门盘开门方位摆收银台 5. 八宅财位放保险柜或收银台 6. 奇门值符位摆吉祥物。案例：上海某餐厅，店东八字喜水，玄空飞星 1 白到向吉，奇门择 2023 年 2 月 14 日午时开张（开门+生门+吉时），开业 3 月内回本。"
    },
    {
      "id": "qfjh_04",
      "category": "八门八宅",
      "title": "奇门八门与八宅方位对应",
      "content": "奇门八门与八宅方位有部分对应：休门（北坎）= 生气位（坎宅东四命）；生门（东北艮）= 延年位（艮宅东四命）；伤门（东震）= 绝命位（西四命忌）；杜门（东南巽）= 生气位（巽宅东四命）；景门（南离）= 天医位（离宅东四命）；死门（西南坤）= 祸害位（西四命忌）；惊门（西兑）= 五鬼位（西四命忌）；开门（西北乾）= 伏位位（乾宅西四命）。合参：奇门吉门方位+八宅吉位 = 双重吉处，用作主卧/书房/财位。"
    },
    {
      "id": "qfjh_05",
      "category": "九星方位",
      "title": "奇门九星与玄空九星异同",
      "content": "奇门九星（天盘）：蓬任冲辅英芮柱心禽 = 八神九星（九星指九星盘）。玄空九星：贪巨禄文廉武破辅弼（洛书九星）。两者区别：奇门九星随天盘转（时辰变星变），玄空九星随元运变（运变星变）。联系：奇门天蓬（贪狼星化）= 玄空贪狼同源；奇门天任 = 玄空巨门；奇门天冲 = 玄空禄存；奇门天辅 = 玄空文曲；奇门天英 = 玄空廉贞；奇门天芮 = 玄空武曲；奇门天柱 = 玄空破军；奇门天心 = 玄空辅弼。"
    },
    {
      "id": "qfjh_06",
      "category": "值符方位",
      "title": "奇门值符方位与风水调整",
      "content": "奇门值符（八神之首）是当时辰的吉神，主管该时辰最吉方位。值符所临之宫位 = 该时辰最吉方位。风水应用：1. 重要决策（如签约/谈判）在值符方位坐 2. 店铺开业时值符位摆财神位 3. 家居重要物品（如保险柜）放在值符位 4. 化解时值符位可放镇宅物。倪海厦：'值符是大将，所到之处百煞退避，是奇门第一吉方'。"
    },
    {
      "id": "qfjh_07",
      "category": "择日要素",
      "title": "奇门择日的关键原则",
      "content": "奇门择日四要素：1. 天时（选黄道吉日，避开四废日、四穷日） 2. 地利（择方位与事主喜用相合） 3. 人和（事主八字与日辰相合） 4. 神助（值符值使吉格）。避忌：1. 五黄月（五黄力士月） 2. 庚申日（八专日） 3. 申日（甲申日不适宜） 4. 月厌日。倪海厦：'奇门择日需精到一柱香（2小时），不可粗略'。"
    },
    {
      "id": "qfjh_08",
      "category": "住宅风水",
      "title": "住宅奇门+八宅综合化解",
      "content": "化解案例：某住宅 2019 年入住后家运衰退，八字分析户主 2020 年入财运大运但实际破财。奇门看：2019 年五黄到中宫 + 流年凶。风水看：八宅生气位在西北方，户主却把厨房设西北（动土），导致生气受冲。化解：1. 改厨房位置至东方（绝命位动火可制煞） 2. 奇门在西北摆泰山石镇宅 3. 调整流年 5 月搬家（避开五黄月）。半年后家运恢复。倪海厦：'风水非迷信，是空间磁场学，调整可改运'。"
    },
    {
      "id": "qfjh_09",
      "category": "商业风水",
      "title": "店铺奇门+玄空旺财布局",
      "content": "店铺旺财三要素：1. 坐向（玄空飞星旺山旺向） 2. 大门（开中门或财门） 3. 收银台（放在财位）。奇门辅助：1. 开业择日用开门+生门+吉格 2. 财位放奇门催财符 3. 每月初在财位焚财神香。案例：广州某服装店，玄空飞星 7 赤到向不利（口舌是非），但奇门择 2023 年 4 月 18 日午时（开门+值符吉）开业，门口加装凸镜化解 7 赤，开业一年营业额反增 30%。倪海厦：'商业风水讲究'形气兼用'，奇门调气，风水调形'。"
    },
    {
      "id": "qfjh_10",
      "category": "化解案例",
      "title": "办公室横梁压顶的奇门+风水化解",
      "content": "横梁压顶是常见煞气，影响坐其下者健康运程。化解：1. 风水：在横梁下挂葫芦或五帝钱 2. 奇门：选择未受横梁压的方位作主座 3. 如必须坐其下，用风水泰山石镇之。案例：上海某公司 CEO 办公桌正对横梁，连续 2 年健康出问题，公司业绩下滑。奇门看：横梁方为五黄煞方+奇门伤门位。化解：将办公桌移到西北（开门吉方） + 横梁下加装天花板遮蔽 + 西北摆铜制风水轮。半年后 CEO 健康恢复，公司业绩翻倍。"
    },
    {
      "id": "qfjh_11",
      "category": "婚嫁应用",
      "title": "婚嫁择日与婚房风水",
      "content": "婚嫁全套：1. 男女双方八字合婚（避免冲克） 2. 奇门择吉日（避开桃花煞日） 3. 奇门择吉时（开门+生门+天喜同到） 4. 婚房风水布置（床放八宅天医位） 5. 婚床奇门方向（按八字喜用方） 6. 床头朝向（按男女生肖六合方）。案例：北京某婚礼，原定 2023 年 5 月 20 日，但奇门看为四废日。改至 6 月 6 日（开门+生门+天喜到日），婚礼顺利，婚后夫妻和睦。"
    },
    {
      "id": "qfjh_12",
      "category": "古代案例",
      "title": "故宫的奇门+风水布局",
      "content": "故宫（紫禁城）是中国古代奇门+风水的集大成：1. 坐北朝南（子山午向，子为冬至阳生，符合'负阴抱阳'风水） 2. 中轴线布局（奇门九宫方位对称） 3. 三大殿（太和殿+中和殿+保和殿 = 三才合和） 4. 金水河绕宫（屈曲来朝，水法第一） 5. 巽方（东南）开门（奇门巽为风，主文运，附会翰林院） 6. 五行配五色（东方青、南方赤、西方白、北方黑、中央黄）。故宫设计者为蒯祥（风水师兼奇门家），凝聚了明代顶级奇门+风水智慧。"
    },
    {
      "id": "qfjh_13",
      "category": "古代案例",
      "title": "天坛的奇门+风水智慧",
      "content": "天坛（皇帝祭天之所）布局：1. 圆形（天圆地方之'天'） 2. 坐北朝南（冬至日出阳光直射圜丘） 3. 圆丘 3 层（奇门九宫中的'三'为生数之首） 4. 9 块石板（九宫之数） 5. 栏板 72 块（代表 72 候） 6. 棂星门 8 根（八卦方位）。倪海厦：'天坛是奇门遁甲的'天盘'落地版，把宇宙气场浓缩到建筑中'。每年冬至祭天，是奇门择日的国家级应用。"
    },
    {
      "id": "qfjh_14",
      "category": "现代应用",
      "title": "办公桌方位的奇门+八字选择",
      "content": "办公桌摆放应综合：1. 八字用神方位（喜木则东方、喜火则南方） 2. 奇门值符方位（当前时辰最吉方） 3. 八宅本命吉方（生气/延年/天医/伏位） 4. 不冲门不背门（不对大门不背对大门坐）。综合方案：八字用神方为主（60% 权重），奇门值符为辅（30%），八宅吉方补足（10%）。倪海厦：'办公桌位置决定 30% 职场运，不可随便'。"
    },
    {
      "id": "qfjh_15",
      "category": "化解方法",
      "title": "五黄煞的奇门+风水化解",
      "content": "五黄煞是风水第一凶星，又称'廉贞五黄'，主灾祸疾病。化解：1. 风水：五黄方安忍水（铜器装盐水）或铜葫芦 2. 奇门：在五黄方焚化太岁符 3. 避免五黄方动土装修 4. 流年五黄飞临的方位需重点化解。倪海厦：'五黄主'静'，不可动；动则发凶'。案例：某宅 2023 年五黄到东南，业主在东南装修厨房导致家人生病。化解：在东南挂铜葫芦+焚太岁符，3 月后家人康复。"
    },
    {
      "id": "qfjh_16",
      "category": "化煞工具",
      "title": "常用化煞工具与奇门配合",
      "content": "化煞工具分 5 类：1. 镇煞类：泰山石、龙龟、麒麟、狮子（镇宅化煞） 2. 化煞类：八卦镜、凸镜、铜葫芦、五帝钱（化解尖角/反弓） 3. 旺财类：金元宝、财神像、貔貅、流水摆件 4. 升学业类：文昌塔、葱、笔筒、毛笔 5. 化桃花类：粉水晶、鸳鸯。奇门配合：1. 选择化煞工具时用奇门择日 2. 摆放化煞工具时面向奇门值符方 3. 化煞完毕后用奇门值符香加持。倪海厦：'化煞工具是形，奇门择日是气，形气结合方有效'。"
    },
    {
      "id": "qfjh_17",
      "category": "误区纠正",
      "title": "奇门风水的常见误区",
      "content": "误区 1：奇门能改一切——错误，奇门是择吉，不能违命 2：风水摆件越贵越好——错误，心诚则灵，关键是摆放位置 3：奇门择日天天可——错误，每月有 5-7 天不可用事 4：罗盘越精密越好——错误，地理环境比罗盘重要 5：大师越老越灵——错误，水平不在年龄。倪海厦：'奇门风水是艺术不是迷信，要用心体会，不可盲从'。"
    },
    {
      "id": "qfjh_18",
      "category": "实操要点",
      "title": "奇门风水的核心心法",
      "content": "倪海厦先生奇门风水心法：1. 奇门为天时（择日择时） 2. 风水为地利（空间布局） 3. 八字为人命（先天禀赋） 4. 三者合一为'天人地合一' 5. 缺一不可但有主次（先看八字定根本，再看奇门定时机，最后看风水调环境） 6. 顺势而为不可逆（命里有时终须有，命里无时莫强求） 7. 日常修行为本（积善之家必有余庆）。倪海厦先生：'奇门风水是术，修行是道；以道御术，术必成；以术求道，道必失'。"
    },
    {
      "id": "qfjh_19",
      "category": "互参方法",
      "title": "奇门风水矛盾时的判断",
      "content": "奇门与风水矛盾时的处理：1. 奇门吉+风水凶 = 短期可成但久后衰败（需先调风水） 2. 奇门凶+风水吉 = 长期平稳但短期不顺（可借奇门择日缓解） 3. 两者都吉 = 大吉，全力投入 4. 两者都凶 = 大凶，宜守不宜进。倪海厦：'矛盾时以风水为体（占 60%），奇门为用（占 40%），因奇门改气快但风水位难调'。案例：某宅风水吉但主人办事总不顺，奇门看是大门开在五黄方，调整后大顺。"
    },
    {
      "id": "qfjh_20",
      "category": "总结心法",
      "title": "奇门风水的现代应用要点",
      "content": "现代应用 7 要点：1. 重大决策前用奇门择日 2. 居住办公用八宅+玄空 3. 商业店铺结合奇门催财 4. 婚嫁嫁娶用奇门选天喜日 5. 出行远游用奇门选天盘吉方 6. 装修动土用奇门避开五黄 7. 健康调理用八宅+奇门定方位。倪海厦总结：'奇门是'时'的艺术，风水是'空'的艺术，二者结合是时空统一的完整体系。现代人应学而时习之，方能趋吉避凶'。"
    }
  ]
}
