{
  "id": "shengxiang",
  "name": "声相与行相详解",
  "description": "五音相法、声音吉凶、说话方式、走路姿态、坐姿睡姿、举止动静，源自《麻衣神相》《柳庄相法》《人伦大统赋》",
  "version": "1.0",
  "entries": [
    {
      "id": "shengxiang_01",
      "title": "五音总论",
      "content": "五音为宫、商、角、徵、羽，对应五行土、金、木、火、水。宫音浑厚沉稳，商音清越响亮，角音高亢悠长，徵音热烈明快，羽音细柔婉转。五音与五脏相通，亦与性格命运相关，音正者主吉，音浊者主凶。"
    },
    {
      "id": "shengxiang_02",
      "title": "宫音相法",
      "content": "宫音属土，对应脾胃，声音浑厚沉稳、节奏缓慢。发宫音者主诚信稳重、宽厚包容，有领导之德，但易保守固执。宫音清亮者主富贵，宫音浊滞者主困顿。宫音与中央、黄色、四季末月相应。"
    },
    {
      "id": "shengxiang_03",
      "title": "商音相法",
      "content": "商音属金，对应肺，声音清越响亮、铿锵有力。发商音者主刚毅果断、有决断力，适合武职、管理，但易刚愎自用。商音清脆者主清贵，商音嘶哑者主刑伤。商音与西方、白色、秋季相应。"
    },
    {
      "id": "shengxiang_04",
      "title": "角音相法",
      "content": "角音属木，对应肝，声音高亢悠长、富有生气。发角音者主仁慈正直、有进取心，适合文职、教育，但易急躁冲动。角音圆润者主福寿，角音尖锐者主孤寡。角音与东方、青色、春季相应。"
    },
    {
      "id": "shengxiang_05",
      "title": "徵音相法",
      "content": "徵音属火，对应心，声音热烈明快、情绪丰富。发徵音者主热情开朗、有感染力，适合演艺、销售，但易情绪波动。徵音明亮者主显达，徵音燥急者主灾祸。徵音与南方、红色、夏季相应。"
    },
    {
      "id": "shengxiang_06",
      "title": "羽音相法",
      "content": "羽音属水，对应肾，声音细柔婉转、圆润动听。发羽音者主聪明机智、善于谋略，适合策划、研究，但易多疑善变。羽音清澈者主智慧，羽音浑浊者主淫欲。羽音与北方、黑色、冬季相应。"
    },
    {
      "id": "shengxiang_07",
      "title": "声音吉凶总论",
      "content": "声音以洪亮、清晰、圆润、持久为佳，主富贵长寿。声音以嘶哑、浑浊、尖利、短促为劣，主贫贱短命。声由心生，心正则声正，心邪则声邪。故听声可以知人之善恶、福祸、寿夭。"
    },
    {
      "id": "shengxiang_08",
      "title": "声音洪亮",
      "content": "声音洪亮如钟磬，余音绕梁，主富贵显达、威望卓著。男子声洪者主事业有成、领导才能，女子声洪者主性格刚强、能掌家权。但过于洪亮而破者主刑克，需配合面相综合判断。"
    },
    {
      "id": "shengxiang_09",
      "title": "声音微弱",
      "content": "声音微弱如蚊蚋，气短声低，主体质虚弱、运势低迷。男子声微者主缺乏魄力、难成大事，女子声微者主柔弱依赖、需人扶持。但声音虽微而清者主清贵，不可一概论凶。"
    },
    {
      "id": "shengxiang_10",
      "title": "声音嘶哑",
      "content": "声音嘶哑如破锣，主刑伤疾病、运势坎坷。先天嘶哑者主先天不足、多灾多难，后天嘶哑者主近期有灾、需注意健康。但从事演艺、歌唱等行业者除外，需结合职业判断。"
    },
    {
      "id": "shengxiang_11",
      "title": "说话方式与性格",
      "content": "说话快者主思维敏捷、性急冲动，说话慢者主深思熟虑、稳重保守。说话多者主外向活泼、易泄露机密，说话少者主内向沉稳、城府较深。说话直者主正直坦诚、易得罪人，说话曲者主圆滑世故、善于周旋。"
    },
    {
      "id": "shengxiang_12",
      "title": "走路姿态相法",
      "content": "走路稳重端正者主心性沉稳、做事可靠，走路轻浮摇摆者主心性不定、难托大事。走路快而急者主性急劳碌，走路慢而缓者主安逸懒散。走路昂首挺胸者主自信有魄力，走路低头含胸者主自卑怯懦。"
    },
    {
      "id": "shengxiang_13",
      "title": "坐姿相法",
      "content": "坐如钟者主端庄稳重、有教养，坐不安者主心性浮躁、缺乏定力。坐姿端正者主正直坦诚，坐姿歪斜者主心术不正。坐时抖腿者主心神不宁、运势不稳，坐时双手抱胸者主防备心强、不易亲近。"
    },
    {
      "id": "shengxiang_14",
      "title": "睡姿相法",
      "content": "仰卧如弓者主福寿安康，俯卧者主性格压抑、易生暗疾，侧卧者主性格平和。睡时安静者主心神安宁、运势平稳，睡时辗转反侧者主心事重重、运势波动。睡时张口者主呼吸系统弱，睡时咬牙者主肝火旺盛。"
    },
    {
      "id": "shengxiang_15",
      "title": "举止动静",
      "content": "举止文雅者主有教养、出身良好，举止粗俗者主缺乏教养、出身寒微。动静得宜者主中庸平和、运势平稳，过于好动者主劳碌奔波，过于好静者主安逸保守。举手投足间可见人之修养、性格、命运。"
    },
    {
      "id": "shengxiang_16",
      "title": "眼神与举止配合",
      "content": "眼神坚定、举止稳重者主有决断力、可托大事，眼神游移、举止轻浮者主心性不定、不可信赖。眼神温和、举止文雅者主仁慈宽厚，眼神锐利、举止果断者主刚毅果决。眼神与举止需配合观察，单看一项易失偏颇。"
    },
    {
      "id": "shengxiang_17",
      "title": "手势相法",
      "content": "手势丰富者主表达能力强、善于沟通，手势稀少者主内向沉稳、不善表达。手势大方者主性格开朗、不拘小节，手势拘谨者主性格内向、谨慎小心。手势指向明确者主目标清晰，手势模糊者主目标不明。"
    },
    {
      "id": "shengxiang_18",
      "title": "声相与五行配合",
      "content": "声相需与五行配合判断。木形人发角音为得位，主吉；发商音为克我，主凶。火形人发徵音为得位，主吉；发羽音为克我，主凶。五行与五音相生相克，需综合判断，不可单论。"
    },
    {
      "id": "shengxiang_19",
      "title": "行相与命运",
      "content": "行相即行走之相，与命运密切相关。龙行虎步者主大贵，鹅行鸭步者主平庸，蛇行鼠步者主奸邪。行走时身体摇摆者主运势波动，行走时身体平稳者主运势稳定。行相可反映人之性格、健康、运势。"
    },
    {
      "id": "shengxiang_20",
      "title": "声相行相综合判断",
      "content": "声相与行相需综合判断，不可偏废。声正行端者主大吉，声邪行曲者主大凶。声正行曲者主心口不一，声邪行端者主外邪内正。综合判断可更准确知人之性格、命运、福祸。"
    }
  ]
}
