{
  "meta": { "name": "紫微斗数辅星杂曜知识库", "version": "1.0", "note": "包含六吉星、六煞星、四化星、禄存天马、红鸾天喜等辅星杂曜详解" },
  "entries": [
    {
      "id": "zuofu",
      "title": "左辅",
      "category": "六吉星",
      "nature": "阳土，助星",
      "content": "左辅为帝相之佐，主助力、辅佐、合作。入命宫则为人忠厚、有包容力、善协调。男命得左辅，事业有贵人相助；女命得左辅，旺夫益子。左辅喜与紫微、天府同宫，能增强主星力量。",
      "palace_effect": "命宫：忠厚有助力；兄弟宫：兄弟和睦互助；夫妻宫：配偶能辅佐；子女宫：子女有助力；财帛宫：财源有辅助；官禄宫：事业有贵人",
      "combo": "左辅+右弼：左右逢源，助力加倍；左辅+文昌：文才辅佐；左辅+天魁：贵人助力"
    },
    {
      "id": "youbi",
      "title": "右弼",
      "category": "六吉星",
      "nature": "阴水，助星",
      "content": "右弼为帝相之佐，主暗助、内助、女性助力。入命宫则为人机敏、善谋略、有女性缘。右弼较左辅更偏阴柔，助力多为暗中相助。女命得右弼，自身能力强，能独当一面。",
      "palace_effect": "命宫：机敏有暗助；兄弟宫：兄弟暗助；夫妻宫：配偶内助；子女宫：子女暗助；财帛宫：暗财有辅助；官禄宫：暗中有贵人",
      "combo": "右弼+左辅：左右逢源；右弼+文曲：才艺辅佐；右弼+天钺：女性贵人"
    },
    {
      "id": "wenchang",
      "title": "文昌",
      "category": "六吉星",
      "nature": "阳金，文星",
      "content": "文昌为文曲星之首，主文采、学识、功名。入命宫则聪明好学、有才华、善考试。文昌喜入命、官禄、福德宫，主科甲功名。文昌化科则文名远播，化忌则文书口舌。",
      "palace_effect": "命宫：聪明有才华；兄弟宫：兄弟有才学；夫妻宫：配偶文雅；子女宫：子女聪明；官禄宫：事业靠文才；福德宫：精神追求高",
      "combo": "文昌+文曲：文星拱命，才华横溢；文昌+化科：科甲高中；文昌+天魁：贵人提携"
    },
    {
      "id": "wenqu",
      "title": "文曲",
      "category": "六吉星",
      "nature": "阴水，才艺星",
      "content": "文曲为才艺之星，主艺术、口才、技艺。与文昌不同，文昌偏正统学术，文曲偏艺术才艺。入命宫则多才多艺、口才好、善表演。文曲化科则艺名远播，化忌则口舌是非。",
      "palace_effect": "命宫：多才多艺；兄弟宫：兄弟有才艺；夫妻宫：配偶有艺术气质；子女宫：子女多艺；官禄宫：事业靠才艺；福德宫：精神生活丰富",
      "combo": "文曲+文昌：才艺双全；文曲+天姚：艺术桃花；文曲+化禄：才艺生财"
    },
    {
      "id": "tiankui",
      "title": "天魁",
      "category": "六吉星",
      "nature": "阳火，贵人星",
      "content": "天魁为天乙贵人，主阳贵、明贵、男性贵人。入命宫则一生多得贵人提携，逢凶化吉。天魁喜入命、迁移、官禄宫，主外有贵人。天魁与年干有关，甲戊庚牛羊，乙己鼠猴乡。",
      "palace_effect": "命宫：一生有贵人；迁移宫：外出遇贵人；官禄宫：事业有提携；财帛宫：财源有贵人；福德宫：精神有寄托",
      "combo": "天魁+天钺：贵人双全；天魁+左辅：助力贵人；天魁+化科：贵人带声望"
    },
    {
      "id": "tianyue",
      "title": "天钺",
      "category": "六吉星",
      "nature": "阴火，贵人星",
      "content": "天钺为玉堂贵人，主阴贵、暗贵、女性贵人。与天魁不同，天魁为明面贵人，天钺为暗中贵人。入命宫则多得女性帮助，或暗中有人提携。天钺亦与年干有关。",
      "palace_effect": "命宫：暗中有贵人；迁移宫：外出遇暗贵；官禄宫：暗中有提携；财帛宫：暗财有贵人；夫妻宫：配偶为贵人",
      "combo": "天钺+天魁：贵人双全；天钺+右弼：暗助贵人；天钺+化禄：贵人带财"
    },
    {
      "id": "lucun",
      "title": "禄存",
      "category": "财星",
      "nature": "阴土，财星",
      "content": "禄存为财星之首，主财富、积蓄、稳定收入。入命宫则一生不愁衣食，善于理财积蓄。禄存喜入命、财帛、田宅宫，主财富丰隆。禄存最忌与空劫同宫，主破财。",
      "palace_effect": "命宫：一生衣食丰足；财帛宫：财源稳定；田宅宫：房产丰厚；官禄宫：事业有财；福德宫：精神富足",
      "combo": "禄存+化禄：双禄交流，大富；禄存+天马：禄马交驰，动中求财；禄存+武曲：财星聚会"
    },
    {
      "id": "tianma",
      "title": "天马",
      "category": "动星",
      "nature": "阳火，动星",
      "content": "天马为驿马星，主动、变动、奔波。入命宫则一生多动，喜变动不喜静止。天马喜与禄存同宫，形成禄马交驰，主动中求财。天马亦主交通工具、远行。",
      "palace_effect": "命宫：一生多奔波；迁移宫：远行有利；官禄宫：事业多变动；财帛宫：动中求财；疾厄宫：注意交通安全",
      "combo": "天马+禄存：禄马交驰，动中求财；天马+天机：机智多变；天马+太阳：光明远行"
    },
    {
      "id": "qingyang",
      "title": "擎羊",
      "category": "六煞星",
      "nature": "阳金，刑星",
      "content": "擎羊为刑克之星，主冲动、刑伤、是非。入命宫则性格刚烈、急躁、易冲动。擎羊喜入辰戌丑未四墓库，能收敛其性；入子午卯酉则刑克重。擎羊与武曲同宫，主武职、外科医生。",
      "palace_effect": "命宫：性格刚烈；兄弟宫：兄弟刑克；夫妻宫：婚姻有摩擦；子女宫：子女缘薄；疾厄宫：易有外伤；官禄宫：事业竞争激烈",
      "combo": "擎羊+火星：火羊相战，冲动加倍；擎羊+陀罗：刑忌交侵；擎羊+武曲：武职权威"
    },
    {
      "id": "tuoluo",
      "title": "陀罗",
      "category": "六煞星",
      "nature": "阴金，忌星",
      "content": "陀罗为拖延之星，主拖延、纠结、反复。入命宫则做事犹豫不决、拖泥带水、易错失良机。陀罗喜与文昌同宫，能化解其拖延；与化忌同宫则纠结加倍。",
      "palace_effect": "命宫：做事拖延；兄弟宫：兄弟关系反复；夫妻宫：婚姻拖延；子女宫：子女缘迟；官禄宫：事业进展慢；福德宫：精神纠结",
      "combo": "陀罗+擎羊：刑忌交侵；陀罗+化忌：纠结拖延；陀罗+文昌：文思拖延"
    },
    {
      "id": "huoxing",
      "title": "火星",
      "category": "六煞星",
      "nature": "阳火，暴星",
      "content": "火星为暴烈之星，主突发、暴躁、意外。入命宫则性格火爆、易冲动、有爆发力。火星喜与铃星同宫，形成火铃交会，主突发之财或突发之灾。火星亦主火灾、炎症。",
      "palace_effect": "命宫：性格火爆；兄弟宫：兄弟冲突；夫妻宫：婚姻有争吵；财帛宫：突发之财或破财；疾厄宫：炎症、发烧；官禄宫：事业有突发变化",
      "combo": "火星+铃星：火铃交会，突发；火星+擎羊：火羊相战；火星+贪狼：火贪爆发"
    },
    {
      "id": "lingxing",
      "title": "铃星",
      "category": "六煞星",
      "nature": "阴火，暗星",
      "content": "铃星为阴火，主暗中的急躁、记仇、暗算。与火星不同，火星为明火爆发，铃星为暗中记恨。入命宫则内心急躁、易记仇、暗中计较。铃星与贪狼同宫，主偏财、横财。",
      "palace_effect": "命宫：内心急躁；兄弟宫：兄弟暗中计较；夫妻宫：婚姻暗中不满；财帛宫：暗财、偏财；官禄宫：暗中竞争；福德宫：精神暗忧",
      "combo": "铃星+火星：火铃交会；铃星+贪狼：铃贪横发；铃星+陀罗：暗忌交加"
    },
    {
      "id": "diyu",
      "title": "地空",
      "category": "六煞星",
      "nature": "阴火，空亡星",
      "content": "地空为空亡之星，主空亡、失落、精神追求。入命宫则思想超脱、不拘世俗、有宗教缘。地空喜入福德、命宫，主精神追求；入财帛则破财，入官禄则事业空幻。",
      "palace_effect": "命宫：思想超脱；财帛宫：财来财去；官禄宫：事业空幻；福德宫：精神追求高；夫妻宫：婚姻有距离感",
      "combo": "地空+地劫：空劫同宫，破财；地空+化禄：禄空则虚；地空+天梁：宗教缘"
    },
    {
      "id": "dijie",
      "title": "地劫",
      "category": "六煞星",
      "nature": "阳火，劫财星",
      "content": "地劫为劫夺之星，主劫夺、破耗、意外损失。与地空不同，地空偏精神空亡，地劫偏物质劫夺。入命宫则易有意外损失、破财、被劫夺。地劫最忌与禄存同宫，主破财。",
      "palace_effect": "命宫：易有意外损失；财帛宫：破财；田宅宫：房产损失；官禄宫：事业被劫夺；迁移宫：外出遇劫",
      "combo": "地劫+地空：空劫同宫，大破；地劫+禄存：禄被劫夺；地劫+化忌：忌劫交加"
    },
    {
      "id": "hongluan",
      "title": "红鸾",
      "category": "桃花星",
      "nature": "阴水，正桃花",
      "content": "红鸾为正桃花星，主婚姻、喜庆、正缘。入命宫则容貌端正、有异性缘、婚姻早。红鸾喜入夫妻宫，主婚姻美满；入命宫则早婚。红鸾与天喜对宫，红鸾主婚，天喜主生育。",
      "palace_effect": "命宫：有正桃花；夫妻宫：婚姻美满；子女宫：子女缘好；福德宫：精神愉悦；迁移宫：外缘好",
      "combo": "红鸾+天喜：鸾喜交会，婚育顺利；红鸾+天姚：桃花重重；红鸾+文昌：文雅桃花"
    },
    {
      "id": "tianxi",
      "title": "天喜",
      "category": "喜庆星",
      "nature": "阳水，喜庆星",
      "content": "天喜为喜庆之星，主生育、喜庆、开心。与红鸾对宫，红鸾主婚，天喜主育。入命宫则为人乐观、喜庆、有子女缘。天喜喜入子女宫，主生育顺利；入福德宫，主精神愉快。",
      "palace_effect": "命宫：乐观喜庆；子女宫：生育顺利；福德宫：精神愉快；夫妻宫：婚姻喜庆；财帛宫：喜庆之财",
      "combo": "天喜+红鸾：鸾喜交会；天喜+天德：喜庆逢贵；天喜+化禄：喜庆带财"
    },
    {
      "id": "tianyao",
      "title": "天姚",
      "category": "桃花星",
      "nature": "阴水，偏桃花",
      "content": "天姚为偏桃花星，主风流、艳遇、艺术气质。与红鸾不同，红鸾为正缘，天姚为偏缘。入命宫则容貌艳丽、有艺术气质、异性缘重。天姚喜与文曲同宫，主艺术才华；忌与化忌同宫，主桃花劫。",
      "palace_effect": "命宫：有艺术气质；夫妻宫：配偶艳丽；官禄宫：事业靠才艺；福德宫：精神浪漫；财帛宫：才艺生财",
      "combo": "天姚+文曲：艺术才华；天姚+红鸾：桃花重重；天姚+化忌：桃花劫"
    },
    {
      "id": "tianxing",
      "title": "天刑",
      "category": "刑星",
      "nature": "阳火，刑克星",
      "content": "天刑为刑克之星，主刑伤、官非、自律。入命宫则为人自律、有原则、易有刑伤。天刑喜入官禄宫，主法律、军警、外科；入疾厄宫则注意手术、外伤。",
      "palace_effect": "命宫：自律有原则；官禄宫：宜从事法律军警；疾厄宫：注意手术外伤；夫妻宫：婚姻有约束；福德宫：精神自律",
      "combo": "天刑+擎羊：刑伤加重；天刑+天梁：刑梁格，主孤克；天刑+化权：权威自律"
    },
    {
      "id": "tianyue_star",
      "title": "天月",
      "category": "病星",
      "nature": "阴水，病星",
      "content": "天月为病星，主疾病、虚弱、慢性病。入命宫则体质较弱、易有慢性病。天月喜与天梁同宫，天梁能解厄；忌与化忌同宫，主疾病缠身。天月入疾厄宫，主健康需特别注意。",
      "palace_effect": "命宫：体质较弱；疾厄宫：慢性病；福德宫：精神忧虑；夫妻宫：配偶体弱；子女宫：子女体质弱",
      "combo": "天月+天梁：梁月同宫，病可解；天月+化忌：忌月交加，病重；天月+擎羊：刑伤带病"
    },
    {
      "id": "tianxun",
      "title": "天虚",
      "category": "虚星",
      "nature": "阴土，虚耗星",
      "content": "天虚为虚耗之星，主虚耗、不实、精神空虚。入命宫则易有虚耗、做事不实、精神空虚。天虚喜与地空同宫，主宗教缘、精神追求；忌与化禄同宫，主虚财。",
      "palace_effect": "命宫：精神空虚；财帛宫：虚财；官禄宫：事业不实；福德宫：精神追求；田宅宫：房产虚耗",
      "combo": "天虚+地空：空虚交加；天虚+化禄：禄虚不实；天虚+天梁：梁虚有解"
    }
  ]
}
